[
    {
        "id": "f707e6de5aa6d775",
        "type": "tab",
        "label": "Sat Control",
        "disabled": false,
        "info": "",
        "env": []
    },
    {
        "id": "5ed311464fc3e048",
        "type": "ui_iframe",
        "z": "f707e6de5aa6d775",
        "group": "59b66a5b4309fe61",
        "name": "",
        "order": 1,
        "width": "32",
        "height": 30,
        "url": "http://192.168.50.41/",
        "origin": "*",
        "scale": "100",
        "x": 590,
        "y": 180,
        "wires": [
            []
        ]
    },
    {
        "id": "4de7b8a656895617",
        "type": "udp in",
        "z": "f707e6de5aa6d775",
        "name": "",
        "iface": "",
        "port": "9932",
        "ipv": "udp4",
        "multicast": "false",
        "group": "224.0.0.1",
        "datatype": "utf8",
        "x": 620,
        "y": 320,
        "wires": [
            [
                "461280de9cdf3fb5"
            ]
        ]
    },
    {
        "id": "461280de9cdf3fb5",
        "type": "debug",
        "z": "f707e6de5aa6d775",
        "name": "debug 551",
        "active": false,
        "tosidebar": true,
        "console": false,
        "tostatus": false,
        "complete": "false",
        "statusVal": "",
        "statusType": "auto",
        "x": 814,
        "y": 294,
        "wires": []
    },
    {
        "id": "bcae0164996898f8",
        "type": "comment",
        "z": "f707e6de5aa6d775",
        "name": "Flow to display CSN S.A.T webpage in Node Red",
        "info": "",
        "x": 180,
        "y": 60,
        "wires": []
    },
    {
        "id": "59b66a5b4309fe61",
        "type": "ui_group",
        "name": "CSN S.A.T",
        "tab": "6d6f25e436f987a2",
        "order": 2,
        "disp": false,
        "width": "32",
        "collapse": false,
        "className": ""
    },
    {
        "id": "6d6f25e436f987a2",
        "type": "ui_tab",
        "name": "Sat Control",
        "icon": "dashboard",
        "order": 15,
        "disabled": false,
        "hidden": false
    }
]